[{"Name":"American Bulldog","good_with_children":"3","good_with_strangers":"0","playfulness":"0"},
{"Name":"Plott Hound","good_with_children":"0","good_with_strangers":"0","playfulness":"0"},
{"Name":"Alaskan Klee Kai","good_with_children":"0","good_with_strangers":"0","playfulness":"0"},
{"Name":"Bullmastiff","good_with_children":"3","good_with_strangers":"3","playfulness":"3"},
{"Name":"Shih Tzu","good_with_children":"5","good_with_strangers":"3","playfulness":"3"},
{"Name":"Pomeranian","good_with_children":"3","good_with_strangers":"3","playfulness":"3"},
{"Name":"Greyhound","good_with_children":"3","good_with_strangers":"3","playfulness":"3"},
{"Name":"Chow Chow","good_with_children":"3","good_with_strangers":"2","playfulness":"3"},
{"Name":"Chinese Shar-Pei","good_with_children":"3","good_with_strangers":"3","playfulness":"3"},
{"Name":"Cocker Spaniel","good_with_children":"5","good_with_strangers":"4","playfulness":"3"},
{"Name":"Great Pyrenees","good_with_children":"3","good_with_strangers":"3","playfulness":"3"},
{"Name":"Newfoundland","good_with_children":"5","good_with_strangers":"5","playfulness":"3"},
{"Name":"Basset Hound","good_with_children":"5","good_with_strangers":"3","playfulness":"3"},
{"Name":"Maltese","good_with_children":"3","good_with_strangers":"3","playfulness":"3"},
{"Name":"Akita","good_with_children":"3","good_with_strangers":"2","playfulness":"3"},
{"Name":"Bloodhound","good_with_children":"3","good_with_strangers":"3","playfulness":"3"},
{"Name":"Komondor","good_with_children":"3","good_with_strangers":"3","playfulness":"3"},
{"Name":"Otterhound","good_with_children":"3","good_with_strangers":"4","playfulness":"3"},
{"Name":"Beauceron","good_with_children":"3","good_with_strangers":"2","playfulness":"3"},
{"Name":"Shiba Inu","good_with_children":"3","good_with_strangers":"3","playfulness":"3"},
{"Name":"Afghan Hound","good_with_children":"3","good_with_strangers":"3","playfulness":"3"},
{"Name":"Chinook","good_with_children":"5","good_with_strangers":"3","playfulness":"3"},
{"Name":"Basenji","good_with_children":"3","good_with_strangers":"3","playfulness":"3"},
{"Name":"Field Spaniel","good_with_children":"5","good_with_strangers":"4","playfulness":"3"},
{"Name":"Japanese Chin","good_with_children":"3","good_with_strangers":"3","playfulness":"3"},
{"Name":"American Eskimo Dog","good_with_children":"5","good_with_strangers":"5","playfulness":"3"},
{"Name":"American Hairless Terrier","good_with_children":"5","good_with_strangers":"3","playfulness":"3"},
{"Name":"American Leopard Hound","good_with_children":"5","good_with_strangers":"3","playfulness":"3"},
{"Name":"American Water Spaniel","good_with_children":"3","good_with_strangers":"3","playfulness":"3"},
{"Name":"Anatolian Shepherd Dog","good_with_children":"3","good_with_strangers":"1","playfulness":"3"},
{"Name":"Barbet","good_with_children":"5","good_with_strangers":"3","playfulness":"3"},
{"Name":"Bergamasco Sheepdog","good_with_children":"3","good_with_strangers":"3","playfulness":"3"},
{"Name":"Berger Picard","good_with_children":"3","good_with_strangers":"3","playfulness":"3"},
{"Name":"Boerboel","good_with_children":"4","good_with_strangers":"3","playfulness":"3"},
{"Name":"Borzoi","good_with_children":"3","good_with_strangers":"3","playfulness":"3"},
{"Name":"Bracco Italiano","good_with_children":"4","good_with_strangers":"3","playfulness":"3"},
{"Name":"Cane Corso","good_with_children":"3","good_with_strangers":"3","playfulness":"3"},
{"Name":"Tibetan Mastiff","good_with_children":"3","good_with_strangers":"1","playfulness":"3"},
{"Name":"Rhodesian Ridgeback","good_with_children":"5","good_with_strangers":"3","playfulness":"3"},
{"Name":"Jindo","good_with_children":"3","good_with_strangers":"3","playfulness":"3"},
{"Name":"Irish Terrier","good_with_children":"5","good_with_strangers":"3","playfulness":"3"},
{"Name":"Cavalier King Charles Spaniel","good_with_children":"5","good_with_strangers":"4","playfulness":"3"},
{"Name":"Alaskan Malamute","good_with_children":"3","good_with_strangers":"3","playfulness":"3"},
{"Name":"Australian Cattle Dog","good_with_children":"3","good_with_strangers":"3","playfulness":"3"},
{"Name":"Belgian Malinois","good_with_children":"3","good_with_strangers":"3","playfulness":"3"},
{"Name":"American Staffordshire Terrier","good_with_children":"3","good_with_strangers":"4","playfulness":"3"},
{"Name":"Golden Retriever","good_with_children":"5","good_with_strangers":"5","playfulness":"4"},
{"Name":"Dachshund","good_with_children":"3","good_with_strangers":"4","playfulness":"4"},
{"Name":"Great Dane","good_with_children":"3","good_with_strangers":"3","playfulness":"4"},
{"Name":"Boxer","good_with_children":"5","good_with_strangers":"4","playfulness":"4"},
{"Name":"Dalmatian","good_with_children":"3","good_with_strangers":"4","playfulness":"4"},
{"Name":"Beagle","good_with_children":"5","good_with_strangers":"3","playfulness":"4"},
{"Name":"Cardigan Welsh Corgi","good_with_children":"4","good_with_strangers":"4","playfulness":"4"},
{"Name":"Bernese Mountain Dog","good_with_children":"5","good_with_strangers":"4","playfulness":"4"},
{"Name":"Bull Terrier","good_with_children":"3","good_with_strangers":"4","playfulness":"4"},
{"Name":"German Longhaired Pointer","good_with_children":"5","good_with_strangers":"4","playfulness":"4"},
{"Name":"Bichon Frise","good_with_children":"5","good_with_strangers":"5","playfulness":"4"},
{"Name":"Chihuahua","good_with_children":"1","good_with_strangers":"2","playfulness":"4"},
{"Name":"Rottweiler","good_with_children":"3","good_with_strangers":"3","playfulness":"4"},
{"Name":"Treeing Walker Coonhound","good_with_children":"5","good_with_strangers":"3","playfulness":"4"},
{"Name":"Giant Schnauzer","good_with_children":"3","good_with_strangers":"3","playfulness":"4"},
{"Name":"Norfolk Terrier","good_with_children":"5","good_with_strangers":"5","playfulness":"4"},
{"Name":"Brittany","good_with_children":"4","good_with_strangers":"3","playfulness":"4"},
{"Name":"Doberman Pinscher","good_with_children":"5","good_with_strangers":"4","playfulness":"4"},
{"Name":"Pekingese","good_with_children":"3","good_with_strangers":"3","playfulness":"4"},
{"Name":"Whippet","good_with_children":"5","good_with_strangers":"3","playfulness":"4"},
{"Name":"Bolognese","good_with_children":"3","good_with_strangers":"3","playfulness":"4"},
{"Name":"Smooth Fox Terrier","good_with_children":"3","good_with_strangers":"3","playfulness":"4"},
{"Name":"Coton de Tulear","good_with_children":"5","good_with_strangers":"5","playfulness":"4"},
{"Name":"Pumi","good_with_children":"3","good_with_strangers":"3","playfulness":"4"},
{"Name":"Xoloitzcuintli","good_with_children":"3","good_with_strangers":"3","playfulness":"4"},
{"Name":"Schipperke","good_with_children":"3","good_with_strangers":"3","playfulness":"4"},
{"Name":"Russian Toy","good_with_children":"3","good_with_strangers":"3","playfulness":"4"},
{"Name":"Italian Greyhound","good_with_children":"3","good_with_strangers":"5","playfulness":"4"},
{"Name":"Hovawart","good_with_children":"4","good_with_strangers":"4","playfulness":"4"},
{"Name":"Miniature Pinscher","good_with_children":"3","good_with_strangers":"3","playfulness":"4"},
{"Name":"Staffordshire Bull Terrier","good_with_children":"5","good_with_strangers":"4","playfulness":"4"},
{"Name":"Australian Shepherd","good_with_children":"5","good_with_strangers":"3","playfulness":"4"},
{"Name":"Pembroke Welsh Corgi","good_with_children":"3","good_with_strangers":"4","playfulness":"4"},
{"Name":"Yorkshire Terrier","good_with_children":"5","good_with_strangers":"5","playfulness":"4"},
{"Name":"Labrador Retriever","good_with_children":"5","good_with_strangers":"5","playfulness":"5"},
{"Name":"Poodle (Miniature)","good_with_children":"5","good_with_strangers":"5","playfulness":"5"},
{"Name":"Border Collie","good_with_children":"3","good_with_strangers":"4","playfulness":"5"},
{"Name":"Siberian Husky","good_with_children":"5","good_with_strangers":"5","playfulness":"5"},
{"Name":"West Highland White Terrier","good_with_children":"5","good_with_strangers":"4","playfulness":"5"},
{"Name":"Pug","good_with_children":"5","good_with_strangers":"5","playfulness":"5"},
{"Name":"Boston Terrier","good_with_children":"5","good_with_strangers":"5","playfulness":"5"},
{"Name":"Vizsla","good_with_children":"5","good_with_strangers":"4","playfulness":"5"},
{"Name":"Shetland Sheepdog","good_with_children":"5","good_with_strangers":"2","playfulness":"5"},
{"Name":"Irish Setter","good_with_children":"5","good_with_strangers":"5","playfulness":"5"},
{"Name":"Havanese","good_with_children":"5","good_with_strangers":"5","playfulness":"5"},
{"Name":"Keeshond","good_with_children":"5","good_with_strangers":"5","playfulness":"5"},
{"Name":"Papillon","good_with_children":"5","good_with_strangers":"5","playfulness":"5"},
{"Name":"Samoyed","good_with_children":"5","good_with_strangers":"5","playfulness":"5"},
{"Name":"Nova Scotia Duck Tolling Retriever","good_with_children":"5","good_with_strangers":"3","playfulness":"5"},
{"Name":"Mudi","good_with_children":"3","good_with_strangers":"3","playfulness":"5"},
{"Name":"French Bulldog","good_with_children":"5","good_with_strangers":"5","playfulness":"5"}]
